vesper/__init__.py
vesper/archive_paths.py
vesper/external_urls.py
vesper/version.py
vesper/archive/__init__.py
vesper/archive/archive.py
vesper/archive/clip_class.py
vesper/archive/detector.py
vesper/archive/recording.py
vesper/archive/station.py
vesper/birdvox/__init__.py
vesper/birdvox/detectors.py
vesper/command/__init__.py
vesper/command/add_recording_audio_files_command.py
vesper/command/annotator.py
vesper/command/classify_command.py
vesper/command/clip_audio_file_export_settings_preset.py
vesper/command/clip_audio_file_exporter.py
vesper/command/clip_exporter.py
vesper/command/clip_hdf5_file_export_settings_preset.py
vesper/command/clip_hdf5_file_exporter.py
vesper/command/clip_metadata_csv_file_exporter.py
vesper/command/clip_set_command.py
vesper/command/clip_table_format_preset.py
vesper/command/command.py
vesper/command/command_utils.py
vesper/command/create_clip_audio_files_command.py
vesper/command/create_random_clips_command.py
vesper/command/delete_clip_audio_files_command.py
vesper/command/delete_clips_command.py
vesper/command/delete_recordings_command.py
vesper/command/detect_command.py
vesper/command/detection_schedule_preset.py
vesper/command/execute_deferred_actions_command.py
vesper/command/export_clip_counts_by_classification_to_csv_file_command.py
vesper/command/export_clip_counts_by_tag_to_csv_file_command.py
vesper/command/export_command.py
vesper/command/import_command.py
vesper/command/job_info.py
vesper/command/job_logging_manager.py
vesper/command/job_manager.py
vesper/command/job_runner.py
vesper/command/metadata_importer.py
vesper/command/recording_importer.py
vesper/command/recording_utils.py
vesper/command/refresh_recording_audio_file_paths_command.py
vesper/command/station_name_aliases_preset.py
vesper/command/tag_clips_command.py
vesper/command/test_command.py
vesper/command/transfer_clip_classifications_command.py
vesper/command/untag_clips_command.py
vesper/django/__init__.py
vesper/django/manage.py
vesper-0.4.14.dist-info/LICENSE
vesper-0.4.14.dist-info/METADATA
vesper-0.4.14.dist-info/WHEEL
vesper-0.4.14.dist-info/entry_points.txt
vesper-0.4.14.dist-info/top_level.txt
vesper-0.4.14.dist-info/RECORD
