Metadata-Version: 2.1
Name: vesper
Version: 0.4.14
Summary: Software for acoustical monitoring of nocturnal bird migration.
Home-page: https://github.com/HaroldMills/Vesper
Author: Harold Mills
Author-email: harold.mills@gmail.com
License: MIT
Classifier: Programming Language :: Python :: 3
Classifier: License :: OSI Approved :: MIT License
Classifier: Operating System :: OS Independent
License-File: LICENSE
Requires-Dist: aioboto3
Requires-Dist: daphne
Requires-Dist: django (~=4.2.0)
Requires-Dist: environs[django]
Requires-Dist: jsonschema
Requires-Dist: psycopg[binary]
Requires-Dist: resampy
Requires-Dist: ruamel-yaml
Requires-Dist: scipy
Requires-Dist: skyfield
Requires-Dist: whitenoise
Requires-Dist: tensorflow (~=2.12.0) ; platform_system != "Darwin" or platform_machine != "arm64"
Requires-Dist: tensorflow-macos (~=2.12.0) ; platform_system == "Darwin" and platform_machine == "arm64"
Requires-Dist: tensorflow-metal (~=0.8.0) ; platform_system == "Darwin" and platform_machine == "arm64"
